{"virus_total": {"IP": {"1.1.1.1": {"data": {"attributes": {"jarm": "27d3ed3ed0003ed1dc42d43d00041d6183ff1bfae51ebd88d70384363d525c", "network": "1.1.1.0/24", "last_https_certificate_date": 1686503647, "tags": ["suspicious-udp"], "last_analysis_date": 1686503344, "as_owner": "CLOUDFLARENET", "last_analysis_stats": {"harmless": 66, "malicious": 4, "suspicious": 0, "undetected": 17, "timeout": 0}, "whois_date": 1684184299, "last_analysis_results": {"Bkav": {"category": "undetected", "result": "unrated", "method": "blacklist", "engine_name": "Bkav"}, "CMC Threat Intelligence": {"category": "harmless", "result": "clean", "method": "blacklist", "engine_name": "CMC Threat Intelligence"}, "Snort IP sample list": {"category": "harmless", "result": "clean", "method": "blacklist", "engine_name": "Snort IP sample list"}, "0xSI_f33d": {"category": "undetected", "result": "unrated", "method": "blacklist", "engine_name": "0xSI_f33d"}, "ViriBack": {"category": "harmless", "result": "clean", "method": "blacklist", "engine_name": "ViriBack"}, "PhishLabs": {"category": "undetected", "result": "unrated", "method": "blacklist", "engine_name": "PhishLabs"}, "K7AntiVirus": {"category": "harmless", "result": "clean", "method": "blacklist", "engine_name": "K7AntiVirus"}, "CINS Army": {"category": "harmless", "result": "clean", "method": "blacklist", "engine_name": "CINS Army"}, "Quttera": {"category": "harmless", "result": "clean", "method": "blacklist", "engine_name": "Quttera"}, "PrecisionSec": {"category": "undetected", "result": "unrated", "method": "blacklist", "engine_name": "PrecisionSec"}, "OpenPhish": {"category": "harmless", "result": "clean", "method": "blacklist", "engine_name": "OpenPhish"}, "VX Vault": {"category": "harmless", "result": "clean", "method": "blacklist", "engine_name": "VX Vault"}, "ArcSight Threat Intelligence": {"category": "undetected", "result": "unrated", "method": "blacklist", "engine_name": "ArcSight Threat Intelligence"}, "Scantitan": {"category": "harmless", "result": "clean", "method": "blacklist", "engine_name": "Scantitan"}, "AlienVault": {"category": "harmless", "result": "clean", "method": "blacklist", "engine_name": "AlienVault"}, "Sophos": {"category": "harmless", "result": "clean", "method": "blacklist", "engine_name": "Sophos"}, "Phishtank": {"category": "harmless", "result": "clean", "method": "blacklist", "engine_name": "Phishtank"}, "Cyan": {"category": "undetected", "result": "unrated", "method": "blacklist", "engine_name": "Cyan"}, "Spam404": {"category": "harmless", "result": "clean", "method": "blacklist", "engine_name": "Spam404"}, "SecureBrain": {"category": "harmless", "result": "clean", "method": "blacklist", "engine_name": "SecureBrain"}, "CRDF": {"category": "harmless", "result": "clean", "method": "blacklist", "engine_name": "CRDF"}, "Fortinet": {"category": "harmless", "result": "clean", "method": "blacklist", "engine_name": "Fortinet"}, "alphaMountain.ai": {"category": "harmless", "result": "clean", "method": "blacklist", "engine_name": "alphaMountain.ai"}, "Lionic": {"category": "harmless", "result": "clean", "method": "blacklist", "engine_name": "Lionic"}, "Cyble": {"category": "harmless", "result": "clean", "method": "blacklist", "engine_name": "Cyble"}, "Seclookup": {"category": "harmless", "result": "clean", "method": "blacklist", "engine_name": "Seclookup"}, "Xcitium Verdict Cloud": {"category": "malicious", "result": "phishing", "method": "blacklist", "engine_name": "Xcitium Verdict Cloud"}, "Google Safebrowsing": {"category": "harmless", "result": "clean", "method": "blacklist", "engine_name": "Google Safebrowsing"}, "SafeToOpen": {"category": "undetected", "result": "unrated", "method": "blacklist", "engine_name": "SafeToOpen"}, "ADMINUSLabs": {"category": "harmless", "result": "clean", "method": "blacklist", "engine_name": "ADMINUSLabs"}, "ESTsecurity": {"category": "harmless", "result": "clean", "method": "blacklist", "engine_name": "ESTsecurity"}, "Juniper Networks": {"category": "harmless", "result": "clean", "method": "blacklist", "engine_name": "Juniper Networks"}, "Heimdal Security": {"category": "harmless", "result": "clean", "method": "blacklist", "engine_name": "Heimdal Security"}, "AutoShun": {"category": "undetected", "result": "unrated", "method": "blacklist", "engine_name": "AutoShun"}, "Trustwave": {"category": "harmless", "result": "clean", "method": "blacklist", "engine_name": "Trustwave"}, "AICC (MONITORAPP)": {"category": "harmless", "result": "clean", "method": "blacklist", "engine_name": "AICC (MONITORAPP)"}, "CyRadar": {"category": "malicious", "result": "malicious", "method": "blacklist", "engine_name": "CyRadar"}, "Dr.Web": {"category": "harmless", "result": "clean", "method": "blacklist", "engine_name": "Dr.Web"}, "Emsisoft": {"category": "harmless", "result": "clean", "method": "blacklist", "engine_name": "Emsisoft"}, "Abusix": {"category": "harmless", "result": "clean", "method": "blacklist", "engine_name": "Abusix"}, "Webroot": {"category": "harmless", "result": "clean", "method": "blacklist", "engine_name": "Webroot"}, "Avira": {"category": "harmless", "result": "clean", "method": "blacklist", "engine_name": "Avira"}, "securolytics": {"category": "harmless", "result": "clean", "method": "blacklist", "engine_name": "securolytics"}, "Antiy-AVL": {"category": "harmless", "result": "clean", "method": "blacklist", "engine_name": "Antiy-AVL"}, "AlphaSOC": {"category": "undetected", "result": "unrated", "method": "blacklist", "engine_name": "AlphaSOC"}, "Acronis": {"category": "harmless", "result": "clean", "method": "blacklist", "engine_name": "Acronis"}, "Quick Heal": {"category": "harmless", "result": "clean", "method": "blacklist", "engine_name": "Quick Heal"}, "URLQuery": {"category": "undetected", "result": "unrated", "method": "blacklist", "engine_name": "URLQuery"}, "Viettel Threat Intelligence": {"category": "harmless", "result": "clean", "method": "blacklist", "engine_name": "Viettel Threat Intelligence"}, "DNS8": {"category": "harmless", "result": "clean", "method": "blacklist", "engine_name": "DNS8"}, "benkow.cc": {"category": "harmless", "result": "clean", "method": "blacklist", "engine_name": "benkow.cc"}, "EmergingThreats": {"category": "harmless", "result": "clean", "method": "blacklist", "engine_name": "EmergingThreats"}, "Chong Lua Dao": {"category": "harmless", "result": "clean", "method": "blacklist", "engine_name": "Chong Lua Dao"}, "Yandex Safebrowsing": {"category": "harmless", "result": "clean", "method": "blacklist", "engine_name": "Yandex Safebrowsing"}, "Lumu": {"category": "undetected", "result": "unrated", "method": "blacklist", "engine_name": "Lumu"}, "zvelo": {"category": "harmless", "result": "clean", "method": "blacklist", "engine_name": "zvelo"}, "Kaspersky": {"category": "harmless", "result": "clean", "method": "blacklist", "engine_name": "Kaspersky"}, "Segasec": {"category": "undetected", "result": "unrated", "method": "blacklist", "engine_name": "Segasec"}, "Sucuri SiteCheck": {"category": "harmless", "result": "clean", "method": "blacklist", "engine_name": "Sucuri SiteCheck"}, "desenmascara.me": {"category": "harmless", "result": "clean", "method": "blacklist", "engine_name": "desenmascara.me"}, "CrowdSec": {"category": "malicious", "result": "malicious", "method": "blacklist", "engine_name": "CrowdSec"}, "Cluster25": {"category": "undetected", "result": "unrated", "method": "blacklist", "engine_name": "Cluster25"}, "URLhaus": {"category": "harmless", "result": "clean", "method": "blacklist", "engine_name": "URLhaus"}, "PREBYTES": {"category": "harmless", "result": "clean", "method": "blacklist", "engine_name": "PREBYTES"}, "StopForumSpam": {"category": "harmless", "result": "clean", "method": "blacklist", "engine_name": "StopForumSpam"}, "Blueliv": {"category": "malicious", "result": "malicious", "method": "blacklist", "engine_name": "Blueliv"}, "Netcraft": {"category": "undetected", "result": "unrated", "method": "blacklist", "engine_name": "Netcraft"}, "ZeroCERT": {"category": "harmless", "result": "clean", "method": "blacklist", "engine_name": "ZeroCERT"}, "Phishing Database": {"category": "harmless", "result": "clean", "method": "blacklist", "engine_name": "Phishing Database"}, "MalwarePatrol": {"category": "harmless", "result": "clean", "method": "blacklist", "engine_name": "MalwarePatrol"}, "IPsum": {"category": "harmless", "result": "clean", "method": "blacklist", "engine_name": "IPsum"}, "Malwared": {"category": "harmless", "result": "clean", "method": "blacklist", "engine_name": "Malwared"}, "BitDefender": {"category": "harmless", "result": "clean", "method": "blacklist", "engine_name": "BitDefender"}, "GreenSnow": {"category": "harmless", "result": "clean", "method": "blacklist", "engine_name": "GreenSnow"}, "G-Data": {"category": "harmless", "result": "clean", "method": "blacklist", "engine_name": "G-Data"}, "VIPRE": {"category": "undetected", "result": "unrated", "method": "blacklist", "engine_name": "VIPRE"}, "SCUMWARE.org": {"category": "harmless", "result": "clean", "method": "blacklist", "engine_name": "SCUMWARE.org"}, "PhishFort": {"category": "undetected", "result": "unrated", "method": "blacklist", "engine_name": "PhishFort"}, "malwares.com URL checker": {"category": "harmless", "result": "clean", "method": "blacklist", "engine_name": "malwares.com URL checker"}, "Forcepoint ThreatSeeker": {"category": "harmless", "result": "clean", "method": "blacklist", "engine_name": "Forcepoint ThreatSeeker"}, "Criminal IP": {"category": "harmless", "result": "clean", "method": "blacklist", "engine_name": "Criminal IP"}, "Certego": {"category": "harmless", "result": "clean", "method": "blacklist", "engine_name": "Certego"}, "ESET": {"category": "harmless", "result": "clean", "method": "blacklist", "engine_name": "ESET"}, "Threatsourcing": {"category": "harmless", "result": "clean", "method": "blacklist", "engine_name": "Threatsourcing"}, "ThreatHive": {"category": "harmless", "result": "clean", "method": "blacklist", "engine_name": "ThreatHive"}, "Bfore.Ai PreCrime": {"category": "harmless", "result": "clean", "method": "blacklist", "engine_name": "Bfore.Ai PreCrime"}}, "reputation": 92, "last_modification_date": 1686508076, "total_votes": {"harmless": 77, "malicious": 13}, "last_https_certificate": {"size": 1529, "public_key": {"ec": {"oid": "secp256r1", "pub": "3059301306072a8648ce3d020106082a8648ce3d03010703420004f1603c98db04431c75fc8bdf7013598ff1ce586105a071f980b4c943e983890dfe22d6aa098ed34fe47fa62718179963568c3b47b8e7ea20b13059158d70a11b"}, "algorithm": "EC"}, "thumbprint_sha256": "98ce6111a81057e7d8d4fdf470278b2fb77781c4bb79bfb31fd31047c388d5a3", "cert_signature": {"signature": "306402303ff8961ba59ad14f007438ef6d43b15dd23a5a0417c159e0fd6aecd86dcfd823d7c838bccb80f9db75df2180dd637290023034b7498beb6240360a4231ddf2ee83ab333d35bbf15055e975f265eaf8f02411807a4bef4124ec6319c2862045ed3318", "signature_algorithm": "1.2.840.10045.4.3.3"}, "validity": {"not_after": "2024-01-11 23:59:59", "not_before": "2023-01-12 00:00:00"}, "version": "V3", "extensions": {"certificate_policies": ["2.23.140.1.2.2"], "extended_key_usage": ["serverAuth", "clientAuth"], "authority_key_identifier": {"keyid": "0abc0829178ca5396d7a0ece33c72eb3edfbc37a"}, "subject_alternative_name": ["cloudflare-dns.com", "*.cloudflare-dns.com", "one.one.one.one", "1.0.0.1", "1.1.1.1", "162.159.36.1", "162.159.46.1", "2606:4700:4700::1001", "2606:4700:4700::1111", "2606:4700:4700::64", "2606:4700:4700::6400"], "subject_key_identifier": "64bad8d7fb54218708f3b28266f99e5f4b7004f2", "crl_distribution_points": ["http://crl3.digicert.com/DigiCertTLSHybridECCSHA3842020CA1-1.crl", "http://crl4.digicert.com/DigiCertTLSHybridECCSHA3842020CA1-1.crl"], "key_usage": ["digitalSignature"], "1.3.6.1.4.1.11129.2.4.2": "048201690167007500eecdd064d5db1acec55cb79db4cd13a23287467cbcecde", "CA": false, "ca_information_access": {"CA Issuers": "http://cacerts.digicert.com/DigiCertTLSHybridECCSHA3842020CA1-1.crt", "OCSP": "http://ocsp.digicert.com"}}, "thumbprint": "17cfe81b0c957357bd6bcd282673003ea72ef216", "serial_number": "3c26a465bd5ed68de8f66f975ce2e5f", "issuer": {"C": "US", "CN": "DigiCert TLS Hybrid ECC SHA384 2020 CA1", "O": "DigiCert Inc"}, "subject": {"C": "US", "L": "San Francisco", "CN": "cloudflare-dns.com", "O": "Cloudflare, Inc.", "ST": "California"}}, "asn": 13335, "whois": "Domain Name: one.one\r\nRegistry Domain ID: DB8D9612E99A84235AF9133FBE4EB27D5-ARI\r\nRegistrar WHOIS Server:\r\nRegistrar URL:\r\nUpdated Date: 2022-07-04T12:15:45Z\r\nCreation Date: 2015-05-20T12:15:44Z\r\nRegistry Expiry Date: 2023-05-20T12:15:44Z\r\nRegistrar: One.com A/S - ONE\r\nRegistrar IANA ID: 9998\r\nRegistrar Abuse Contact Email:\r\nRegistrar Abuse Contact Phone:\r\nDomain Status: ok https://icann.org/epp#ok\r\nRegistry Registrant ID: REDACTED FOR PRIVACY\r\nRegistrant Name: REDACTED FOR PRIVACY\r\nRegistrant Organization: One.com A/S\r\nRegistrant Street: REDACTED FOR PRIVACY\r\nRegistrant Street: REDACTED FOR PRIVACY\r\nRegistrant Street: REDACTED FOR PRIVACY\r\nRegistrant City: REDACTED FOR PRIVACY\r\nRegistrant State/Province:\r\nRegistrant Postal Code: REDACTED FOR PRIVACY\r\nRegistrant Country: dk\r\nRegistrant Phone: REDACTED FOR PRIVACY\r\nRegistrant Phone Ext: REDACTED FOR PRIVACY\r\nRegistrant Fax: REDACTED FOR PRIVACY\r\nRegistrant Fax Ext: REDACTED FOR PRIVACY\r\nRegistrant Email: Please query the RDDS service of the Registrar of Record identified in this output for information on how to contact the Registrant, Admin, or Tech contact of the queried domain name.\r\nRegistry Admin ID: REDACTED FOR PRIVACY\r\nAdmin Name: REDACTED FOR PRIVACY\r\nAdmin Organization: REDACTED FOR PRIVACY\r\nAdmin Street: REDACTED FOR PRIVACY\r\nAdmin Street: REDACTED FOR PRIVACY\r\nAdmin Street: REDACTED FOR PRIVACY\r\nAdmin City: REDACTED FOR PRIVACY\r\nAdmin State/Province: REDACTED FOR PRIVACY\r\nAdmin Postal Code: REDACTED FOR PRIVACY\r\nAdmin Country: REDACTED FOR PRIVACY\r\nAdmin Phone: REDACTED FOR PRIVACY\r\nAdmin Phone Ext: REDACTED FOR PRIVACY\r\nAdmin Fax: REDACTED FOR PRIVACY\r\nAdmin Fax Ext: REDACTED FOR PRIVACY\r\nAdmin Email: Please query the RDDS service of the Registrar of Record identified in this output for information on how to contact the Registrant, Admin, or Tech contact of the queried domain name.\r\nRegistry Tech ID: REDACTED FOR PRIVACY\r\nTech Name: REDACTED FOR PRIVACY\r\nTech Organization: REDACTED FOR PRIVACY\r\nTech Street: REDACTED FOR PRIVACY\r\nTech Street: REDACTED FOR PRIVACY\r\nTech Street: REDACTED FOR PRIVACY\r\nTech City: REDACTED FOR PRIVACY\r\nTech State/Province: REDACTED FOR PRIVACY\r\nTech Postal Code: REDACTED FOR PRIVACY\r\nTech Country: REDACTED FOR PRIVACY\r\nTech Phone: REDACTED FOR PRIVACY\r\nTech Phone Ext: REDACTED FOR PRIVACY\r\nTech Fax: REDACTED FOR PRIVACY\r\nTech Fax Ext: REDACTED FOR PRIVACY\r\nTech Email: Please query the RDDS service of the Registrar of Record identified in this output for information on how to contact the Registrant, Admin, or Tech contact of the queried domain name.\r\nName Server: a.b-one-dns.net\r\nName Server: b.b-one-dns.net\r\nDNSSEC: signedDelegation\r\nURL of the ICANN Whois Inaccuracy Complaint Form: https://www.icann.org/wicf/\r\n>>> Last update of WHOIS database: 2023-05-15T20:58:18Z <<<\r\n\r\nFor more information on Whois status codes, please visit https://icann.org/epp\r\n\r\nThe Service is provided so that you may look up certain information in relation to domain names that we store in our database.\r\n\r\nUse of the Service is subject to our policies, in particular you should familiarise yourself with our Acceptable Use Policy and our Privacy Policy.\r\n\r\nThe information provided by this Service is 'as is' and we make no guarantee of it its accuracy.\r\n\r\nYou agree that by your use of the Service you will not use the information provided by us in a way which is:\r\n* inconsistent with any applicable laws,\r\n* inconsistent with any policy issued by us,\r\n* to generate, distribute, or facilitate unsolicited mass email, promotions, advertisings or other solicitations, or\r\n* to enable high volume, automated, electronic processes that apply to the Service.\r\n\r\nYou acknowledge that:\r\n* a response from the Service that a domain name is 'available', does not guarantee that is able to be registered,\r\n* we may restrict, suspend or terminate your access to the Service at any time, and\r\n* the copying, compilation, repackaging, dissemination or other use of the information provided by the Service is not permitted, without our express written consent.\r\n\r\nThis information has been prepared and published in order to represent administrative and technical management of the TLD.\r\n\r\nWe may discontinue or amend any part or the whole of these Terms of Service from time to time at our absolute discretion.\r\n"}, "type": "ip_address", "id": "1.1.1.1", "links": {"self": "https://www.virustotal.com/api/v3/ip_addresses/1.1.1.1"}}}, "www.google.com": {"data": {"attributes": {"last_dns_records": [{"type": "A", "value": "142.250.203.100", "ttl": 300}, {"type": "AAAA", "value": "2a00:1450:400a:808::2004", "ttl": 300}], "jarm": "27d40d40d29d40d1dc42d43d00041d4689ee210389f4f6b4b5b1b93f92252d", "whois": "Admin Country: US\nAdmin Organization: Google LLC\nAdmin State/Province: CA\nCreation Date: 1997-09-15T04:00:00Z\nCreation Date: 1997-09-15T07:00:00+0000\nDNSSEC: unsigned\nDomain Name: GOOGLE.COM\nDomain Name: google.com\nDomain Status: clientDeleteProhibited (https://www.icann.org/epp#clientDeleteProhibited)\nDomain Status: clientDeleteProhibited https://icann.org/epp#clientDeleteProhibited\nDomain Status: clientTransferProhibited (https://www.icann.org/epp#clientTransferProhibited)\nDomain Status: clientTransferProhibited https://icann.org/epp#clientTransferProhibited\nDomain Status: clientUpdateProhibited (https://www.icann.org/epp#clientUpdateProhibited)\nDomain Status: clientUpdateProhibited https://icann.org/epp#clientUpdateProhibited\nDomain Status: serverDeleteProhibited (https://www.icann.org/epp#serverDeleteProhibited)\nDomain Status: serverDeleteProhibited https://icann.org/epp#serverDeleteProhibited\nDomain Status: serverTransferProhibited (https://www.icann.org/epp#serverTransferProhibited)\nDomain Status: serverTransferProhibited https://icann.org/epp#serverTransferProhibited\nDomain Status: serverUpdateProhibited (https://www.icann.org/epp#serverUpdateProhibited)\nDomain Status: serverUpdateProhibited https://icann.org/epp#serverUpdateProhibited\nName Server: NS1.GOOGLE.COM\nName Server: NS2.GOOGLE.COM\nName Server: NS3.GOOGLE.COM\nName Server: NS4.GOOGLE.COM\nName Server: ns1.google.com\nName Server: ns2.google.com\nName Server: ns3.google.com\nName Server: ns4.google.com\nRegistrant Country: US\nRegistrant Email: ca4484b9e50182bds@\nRegistrant Organization: 3307059bbb3149c4\nRegistrant State/Province: b1952dfc047df18a\nRegistrar Abuse Contact Email: abusecomplaints@markmonitor.com\nRegistrar Abuse Contact Phone: +1.2086851750\nRegistrar IANA ID: 292\nRegistrar Registration Expiration Date: 2028-09-13T07:00:00+0000\nRegistrar URL: http://www.markmonitor.com\nRegistrar WHOIS Server: whois.markmonitor.com\nRegistrar: MarkMonitor Inc.\nRegistrar: MarkMonitor, Inc.\nRegistry Domain ID: 2138514_DOMAIN_COM-VRSN\nRegistry Expiry Date: 2028-09-14T04:00:00Z\nTech Country: US\nTech Organization: Google LLC\nTech State/Province: CA\nUpdated Date: 2019-09-09T15:39:04+0000\nUpdated Date: 2019-09-09T15:39:04Z", "last_https_certificate_date": 1686441623, "tags": [], "popularity_ranks": {"Cisco Umbrella": {"timestamp": 1686502681, "rank": 3}}, "last_analysis_date": 1686441615, "last_dns_records_date": 1686441623, "last_analysis_stats": {"harmless": 70, "malicious": 1, "suspicious": 0, "undetected": 16, "timeout": 0}, "creation_date": 874306800, "reputation": 196, "registrar": "MarkMonitor Inc.", "last_analysis_results": {"Bkav": {"category": "undetected", "result": "unrated", "method": "blacklist", "engine_name": "Bkav"}, "CMC Threat Intelligence": {"category": "malicious", "result": "malicious", "method": "blacklist", "engine_name": "CMC Threat Intelligence"}, "Snort IP sample list": {"category": "harmless", "result": "clean", "method": "blacklist", "engine_name": "Snort IP sample list"}, "0xSI_f33d": {"category": "undetected", "result": "unrated", "method": "blacklist", "engine_name": "0xSI_f33d"}, "ViriBack": {"category": "harmless", "result": "clean", "method": "blacklist", "engine_name": "ViriBack"}, "PhishLabs": {"category": "harmless", "result": "clean", "method": "blacklist", "engine_name": "PhishLabs"}, "K7AntiVirus": {"category": "harmless", "result": "clean", "method": "blacklist", "engine_name": "K7AntiVirus"}, "CINS Army": {"category": "harmless", "result": "clean", "method": "blacklist", "engine_name": "CINS Army"}, "Quttera": {"category": "harmless", "result": "clean", "method": "blacklist", "engine_name": "Quttera"}, "PrecisionSec": {"category": "undetected", "result": "unrated", "method": "blacklist", "engine_name": "PrecisionSec"}, "OpenPhish": {"category": "harmless", "result": "clean", "method": "blacklist", "engine_name": "OpenPhish"}, "VX Vault": {"category": "harmless", "result": "clean", "method": "blacklist", "engine_name": "VX Vault"}, "ArcSight Threat Intelligence": {"category": "undetected", "result": "unrated", "method": "blacklist", "engine_name": "ArcSight Threat Intelligence"}, "Scantitan": {"category": "harmless", "result": "clean", "method": "blacklist", "engine_name": "Scantitan"}, "AlienVault": {"category": "harmless", "result": "clean", "method": "blacklist", "engine_name": "AlienVault"}, "Sophos": {"category": "harmless", "result": "clean", "method": "blacklist", "engine_name": "Sophos"}, "Phishtank": {"category": "harmless", "result": "clean", "method": "blacklist", "engine_name": "Phishtank"}, "Cyan": {"category": "undetected", "result": "unrated", "method": "blacklist", "engine_name": "Cyan"}, "Spam404": {"category": "harmless", "result": "clean", "method": "blacklist", "engine_name": "Spam404"}, "SecureBrain": {"category": "harmless", "result": "clean", "method": "blacklist", "engine_name": "SecureBrain"}, "CRDF": {"category": "harmless", "result": "clean", "method": "blacklist", "engine_name": "CRDF"}, "Fortinet": {"category": "harmless", "result": "clean", "method": "blacklist", "engine_name": "Fortinet"}, "alphaMountain.ai": {"category": "harmless", "result": "clean", "method": "blacklist", "engine_name": "alphaMountain.ai"}, "Lionic": {"category": "harmless", "result": "clean", "method": "blacklist", "engine_name": "Lionic"}, "Cyble": {"category": "harmless", "result": "clean", "method": "blacklist", "engine_name": "Cyble"}, "Seclookup": {"category": "harmless", "result": "clean", "method": "blacklist", "engine_name": "Seclookup"}, "Xcitium Verdict Cloud": {"category": "harmless", "result": "clean", "method": "blacklist", "engine_name": "Xcitium Verdict Cloud"}, "Google Safebrowsing": {"category": "harmless", "result": "clean", "method": "blacklist", "engine_name": "Google Safebrowsing"}, "SafeToOpen": {"category": "undetected", "result": "unrated", "method": "blacklist", "engine_name": "SafeToOpen"}, "ADMINUSLabs": {"category": "harmless", "result": "clean", "method": "blacklist", "engine_name": "ADMINUSLabs"}, "ESTsecurity": {"category": "harmless", "result": "clean", "method": "blacklist", "engine_name": "ESTsecurity"}, "Juniper Networks": {"category": "harmless", "result": "clean", "method": "blacklist", "engine_name": "Juniper Networks"}, "Heimdal Security": {"category": "harmless", "result": "clean", "method": "blacklist", "engine_name": "Heimdal Security"}, "AutoShun": {"category": "undetected", "result": "unrated", "method": "blacklist", "engine_name": "AutoShun"}, "Trustwave": {"category": "harmless", "result": "clean", "method": "blacklist", "engine_name": "Trustwave"}, "AICC (MONITORAPP)": {"category": "harmless", "result": "clean", "method": "blacklist", "engine_name": "AICC (MONITORAPP)"}, "CyRadar": {"category": "harmless", "result": "clean", "method": "blacklist", "engine_name": "CyRadar"}, "Dr.Web": {"category": "harmless", "result": "clean", "method": "blacklist", "engine_name": "Dr.Web"}, "Emsisoft": {"category": "harmless", "result": "clean", "method": "blacklist", "engine_name": "Emsisoft"}, "Abusix": {"category": "harmless", "result": "clean", "method": "blacklist", "engine_name": "Abusix"}, "Webroot": {"category": "harmless", "result": "clean", "method": "blacklist", "engine_name": "Webroot"}, "Avira": {"category": "harmless", "result": "clean", "method": "blacklist", "engine_name": "Avira"}, "securolytics": {"category": "harmless", "result": "clean", "method": "blacklist", "engine_name": "securolytics"}, "Antiy-AVL": {"category": "harmless", "result": "clean", "method": "blacklist", "engine_name": "Antiy-AVL"}, "AlphaSOC": {"category": "undetected", "result": "unrated", "method": "blacklist", "engine_name": "AlphaSOC"}, "Acronis": {"category": "harmless", "result": "clean", "method": "blacklist", "engine_name": "Acronis"}, "Quick Heal": {"category": "harmless", "result": "clean", "method": "blacklist", "engine_name": "Quick Heal"}, "URLQuery": {"category": "harmless", "result": "clean", "method": "blacklist", "engine_name": "URLQuery"}, "Viettel Threat Intelligence": {"category": "harmless", "result": "clean", "method": "blacklist", "engine_name": "Viettel Threat Intelligence"}, "DNS8": {"category": "harmless", "result": "clean", "method": "blacklist", "engine_name": "DNS8"}, "benkow.cc": {"category": "harmless", "result": "clean", "method": "blacklist", "engine_name": "benkow.cc"}, "EmergingThreats": {"category": "harmless", "result": "clean", "method": "blacklist", "engine_name": "EmergingThreats"}, "Chong Lua Dao": {"category": "harmless", "result": "clean", "method": "blacklist", "engine_name": "Chong Lua Dao"}, "Yandex Safebrowsing": {"category": "harmless", "result": "clean", "method": "blacklist", "engine_name": "Yandex Safebrowsing"}, "Lumu": {"category": "undetected", "result": "unrated", "method": "blacklist", "engine_name": "Lumu"}, "zvelo": {"category": "harmless", "result": "clean", "method": "blacklist", "engine_name": "zvelo"}, "Kaspersky": {"category": "harmless", "result": "clean", "method": "blacklist", "engine_name": "Kaspersky"}, "Segasec": {"category": "harmless", "result": "clean", "method": "blacklist", "engine_name": "Segasec"}, "Sucuri SiteCheck": {"category": "harmless", "result": "clean", "method": "blacklist", "engine_name": "Sucuri SiteCheck"}, "desenmascara.me": {"category": "harmless", "result": "clean", "method": "blacklist", "engine_name": "desenmascara.me"}, "CrowdSec": {"category": "undetected", "result": "unrated", "method": "blacklist", "engine_name": "CrowdSec"}, "Cluster25": {"category": "undetected", "result": "unrated", "method": "blacklist", "engine_name": "Cluster25"}, "URLhaus": {"category": "harmless", "result": "clean", "method": "blacklist", "engine_name": "URLhaus"}, "PREBYTES": {"category": "harmless", "result": "clean", "method": "blacklist", "engine_name": "PREBYTES"}, "StopForumSpam": {"category": "harmless", "result": "clean", "method": "blacklist", "engine_name": "StopForumSpam"}, "Blueliv": {"category": "harmless", "result": "clean", "method": "blacklist", "engine_name": "Blueliv"}, "Netcraft": {"category": "undetected", "result": "unrated", "method": "blacklist", "engine_name": "Netcraft"}, "ZeroCERT": {"category": "harmless", "result": "clean", "method": "blacklist", "engine_name": "ZeroCERT"}, "Phishing Database": {"category": "harmless", "result": "clean", "method": "blacklist", "engine_name": "Phishing Database"}, "MalwarePatrol": {"category": "harmless", "result": "clean", "method": "blacklist", "engine_name": "MalwarePatrol"}, "IPsum": {"category": "harmless", "result": "clean", "method": "blacklist", "engine_name": "IPsum"}, "Malwared": {"category": "harmless", "result": "clean", "method": "blacklist", "engine_name": "Malwared"}, "BitDefender": {"category": "harmless", "result": "clean", "method": "blacklist", "engine_name": "BitDefender"}, "GreenSnow": {"category": "harmless", "result": "clean", "method": "blacklist", "engine_name": "GreenSnow"}, "G-Data": {"category": "harmless", "result": "clean", "method": "blacklist", "engine_name": "G-Data"}, "VIPRE": {"category": "undetected", "result": "unrated", "method": "blacklist", "engine_name": "VIPRE"}, "SCUMWARE.org": {"category": "harmless", "result": "clean", "method": "blacklist", "engine_name": "SCUMWARE.org"}, "PhishFort": {"category": "undetected", "result": "unrated", "method": "blacklist", "engine_name": "PhishFort"}, "malwares.com URL checker": {"category": "harmless", "result": "clean", "method": "blacklist", "engine_name": "malwares.com URL checker"}, "Forcepoint ThreatSeeker": {"category": "harmless", "result": "clean", "method": "blacklist", "engine_name": "Forcepoint ThreatSeeker"}, "Criminal IP": {"category": "undetected", "result": "unrated", "method": "blacklist", "engine_name": "Criminal IP"}, "Certego": {"category": "harmless", "result": "clean", "method": "blacklist", "engine_name": "Certego"}, "ESET": {"category": "harmless", "result": "clean", "method": "blacklist", "engine_name": "ESET"}, "Threatsourcing": {"category": "harmless", "result": "clean", "method": "blacklist", "engine_name": "Threatsourcing"}, "ThreatHive": {"category": "harmless", "result": "clean", "method": "blacklist", "engine_name": "ThreatHive"}, "Bfore.Ai PreCrime": {"category": "harmless", "result": "clean", "method": "blacklist", "engine_name": "Bfore.Ai PreCrime"}}, "last_update_date": 1568043544, "last_modification_date": 1686517212, "tld": "com", "last_https_certificate": {"public_key": {"algorithm": "EC", "ec": {"oid": "secp256r1", "pub": "3059301306072a8648ce3d020106082a8648ce3d03010703420004e7e24ed3b505f9892a53b187bef3c5045b932386de114793b54aeb5d70d5938ff204c03b69f15552888de131777f5891f5961bdfda1fc5079123789bbc37281f"}}, "thumbprint_sha256": "de323320be6ab0baf76489cc96737ba3816b45e3b0fedd1fd52322421615e027", "thumbprint": "a895c3cbd63fbc0a7dff36725e2f56269feb770e", "subject": {"CN": "www.google.com"}, "validity": {"not_after": "2023-08-11 12:58:12", "not_before": "2023-05-19 12:58:13"}, "version": "V3", "extensions": {"certificate_policies": ["2.23.140.1.2.1", "1.3.6.1.4.1.11129.2.5.3"], "extended_key_usage": ["serverAuth"], "authority_key_identifier": {"keyid": "8a747faf85cdee95cd3d9cd0e24614f371351d27"}, "subject_alternative_name": ["www.google.com"], "ca_information_access": {"CA Issuers": "http://pki.goog/repo/certs/gts1c3.der", "OCSP": "http://ocsp.pki.goog/gts1c3"}, "subject_key_identifier": "95c5e6af1cd6d2002a8abfd76b26db39ec94fa07", "crl_distribution_points": ["http://crls.pki.goog/gts1c3/fVJxbV-Ktmk.crl"], "key_usage": ["digitalSignature"], "1.3.6.1.4.1.11129.2.4.2": "0481f200f0007600e83ed0da3ef5063532e75728bc896bc903d3cbd1116beceb", "CA": false}, "cert_signature": {"signature_algorithm": "sha256RSA", "signature": "d06e113930604073ac15eebb58723323a54e0d8f94e8e200adff26b27c5f138d581f6f2771e998a60f41aea11ad3b65e5410e010c35d6c26797acb3372daf4d7f890c1cceca9a14d4bba352c9c20dbaf178c36f0ac643f4cbe5513699af9bb93bdb7c4693eec5923761a403210fbdf6d8531996a615df00d10c41da4833599c19d39e235a5b1f9c5e33ef9461eb632a23699d91efe71030653ef937ef19eca43eda27f8adc23eb180d0d828871cf2a8ecb9c753f2dd1b4bad46421f2dc9bb1b6e5ff16f94c5c3bb4600a141dfaa1981a12a968fcb072dbfbe7397780163b8ae18c716f178fc254792ec5e84a976cadc06219aa2b0959184e898ab4aea8f380b4"}, "serial_number": "688a9d708922429412bb41ddc046521", "issuer": {"C": "US", "CN": "GTS CA 1C3", "O": "Google Trust Services LLC"}, "size": 1163}, "categories": {"Forcepoint ThreatSeeker": "search engines and portals", "Sophos": "search engines", "Xcitium Verdict Cloud": "mobile communications", "BitDefender": "searchengines"}, "total_votes": {"harmless": 72, "malicious": 14}}, "type": "domain", "id": "www.google.com", "links": {"self": "https://www.virustotal.com/api/v3/domains/www.google.com"}}}}, "<class 'lib.class_helper.ContextProcess'>": {"ccdef4b25564f424772317356e27e6aa51976d2805594024b30f7b852f1ccf34": {"scans": {"Bkav": {"detected": true, "version": "1.3.0.10239", "result": "W32.RamreaX.Trojan", "update": "20190604"}, "Lionic": {"detected": true, "version": "4.2", "result": "Trojan.Win32.Generic.4!c", "update": "20190604"}, "MicroWorld-eScan": {"detected": true, "version": "14.0.297.0", "result": "Gen:Variant.Ursu.368581", "update": "20190604"}, "FireEye": {"detected": true, "version": "29.7.0.0", "result": "Generic.mg.9f97a5dd3792cdcc", "update": "20190605"}, "CAT-QuickHeal": {"detected": true, "version": "14.00", "result": "Trojan.Generic", "update": "20190604"}, "McAfee": {"detected": true, "version": "6.0.6.653", "result": "GenericRXGV-AJ!9F97A5DD3792", "update": "20190605"}, "Cylance": {"detected": true, "version": "2.3.1.101", "result": "Unsafe", "update": "20190605"}, "Paloalto": {"detected": false, "version": "1.0", "result": null, "update": "20190605"}, "Trustlook": {"detected": false, "version": "1.0", "result": null, "update": "20190605"}, "Alibaba": {"detected": true, "version": "0.3.0.5", "result": "Trojan:Win32/Kryptik.4a9e124e", "update": "20190527"}, "K7GW": {"detected": true, "version": "11.48.31122", "result": "Riskware ( 0040eff71 )", "update": "20190604"}, "K7AntiVirus": {"detected": true, "version": "11.46.31063", "result": "Riskware ( 0040eff71 )", "update": "20190529"}, "Invincea": {"detected": true, "version": "6.3.6.26157", "result": "heuristic", "update": "20190525"}, "Baidu": {"detected": false, "version": "1.0.0.2", "result": null, "update": "20190318"}, "Babable": {"detected": false, "version": "9107201", "result": null, "update": "20190424"}, "F-Prot": {"detected": true, "version": "4.7.1.166", "result": "W32/Kryptik.PK.gen!Eldorado", "update": "20190604"}, "Symantec": {"detected": true, "version": "1.9.0.0", "result": "ML.Attribute.HighConfidence", "update": "20190604"}, "TotalDefense": {"detected": false, "version": "37.1.62.1", "result": null, "update": "20190604"}, "APEX": {"detected": true, "version": "5.24", "result": "Malicious", "update": "20190604"}, "Avast": {"detected": true, "version": "18.4.3895.0", "result": "Win32:ReposFxg-F [Trj]", "update": "20190604"}, "ClamAV": {"detected": true, "version": "0.101.2.0", "result": "Win.Malware.Unsafe-6818525-0", "update": "20190604"}, "Kaspersky": {"detected": true, "version": "15.0.1.13", "result": "HEUR:Trojan.Win32.Generic", "update": "20190604"}, "BitDefender": {"detected": true, "version": "7.2", "result": "Gen:Variant.Ursu.368581", "update": "20190604"}, "NANO-Antivirus": {"detected": true, "version": "1.0.134.24826", "result": "Trojan.Win32.Tofsee.fmaayb", "update": "20190604"}, "SUPERAntiSpyware": {"detected": false, "version": "5.6.0.1032", "result": null, "update": "20190604"}, "Tencent": {"detected": true, "version": "1.0.0.1", "result": "Win32.Trojan.Kryptik.Hxqd", "update": "20190605"}, "Ad-Aware": {"detected": true, "version": "3.0.5.370", "result": "Gen:Variant.Ursu.368581", "update": "20190604"}, "Emsisoft": {"detected": true, "version": "2018.4.0.1029", "result": "Gen:Variant.Ursu.368581 (B)", "update": "20190604"}, "Comodo": {"detected": true, "version": "30972", "result": "TrojWare.Win32.Tofsee.MF@80rtv8", "update": "20190605"}, "F-Secure": {"detected": true, "version": "12.0.86.52", "result": "Heuristic.HEUR/AGEN.1037843", "update": "20190605"}, "DrWeb": {"detected": true, "version": "7.0.34.11020", "result": "BackDoor.Tofsee.192", "update": "20190604"}, "Zillya": {"detected": true, "version": "2.0.0.3825", "result": "Backdoor.Tofsee.Win32.2205", "update": "20190604"}, "TrendMicro": {"detected": true, "version": "10.0.0.1040", "result": "TROJ_GEN.R002C0PB319", "update": "20190604"}, "McAfee-GW-Edition": {"detected": true, "version": "v2017.3010", "result": "GenericRXGV-AJ!9F97A5DD3792", "update": "20190604"}, "CMC": {"detected": false, "version": "1.1.0.977", "result": null, "update": "20190321"}, "TheHacker": {"detected": false, "version": "6.8.0.5.4249", "result": null, "update": "20190601"}, "SentinelOne": {"detected": true, "version": "1.0.27.333", "result": "DFI - Malicious PE", "update": "20190604"}, "Cyren": {"detected": true, "version": "6.2.0.1", "result": "W32/Kryptik.PK.gen!Eldorado", "update": "20190604"}, "Jiangmin": {"detected": true, "version": "16.0.100", "result": "Backdoor.Tofsee.anl", "update": "20190529"}, "Webroot": {"detected": false, "version": "1.0.0.403", "result": null, "update": "20190605"}, "Avira": {"detected": true, "version": "8.3.3.8", "result": "HEUR/AGEN.1037843", "update": "20190604"}, "Fortinet": {"detected": true, "version": "5.4.247.0", "result": "W32/Tofsee.BJ!tr", "update": "20190604"}, "Antiy-AVL": {"detected": true, "version": "3.0.0.1", "result": "Trojan[Backdoor]/Win32.Tofsee", "update": "20190604"}, "Kingsoft": {"detected": false, "version": "2013.8.14.323", "result": null, "update": "20190605"}, "Endgame": {"detected": true, "version": "3.0.12", "result": "malicious (high confidence)", "update": "20190522"}, "Arcabit": {"detected": true, "version": "1.0.0.846", "result": "Trojan.Ursu.D59FC5", "update": "20190605"}, "ViRobot": {"detected": false, "version": "2014.3.20.0", "result": null, "update": "20190604"}, "ZoneAlarm": {"detected": true, "version": "1.0", "result": "HEUR:Trojan.Win32.Generic", "update": "20190604"}, "Avast-Mobile": {"detected": false, "version": "190604-04", "result": null, "update": "20190604"}, "Microsoft": {"detected": true, "version": "1.1.16000.6", "result": "Trojan:Win32/Occamy.C", "update": "20190604"}, "TACHYON": {"detected": false, "version": "2019-06-04.02", "result": null, "update": "20190604"}, "Sophos": {"detected": true, "version": "4.98.0", "result": "Mal/Elenoocka-G", "update": "20190604"}, "AhnLab-V3": {"detected": true, "version": "3.15.2.24317", "result": "Trojan/Win32.Monder.R251841", "update": "20190604"}, "Acronis": {"detected": true, "version": "1.0.1.51", "result": "suspicious", "update": "20190604"}, "VBA32": {"detected": true, "version": "4.0.0", "result": "BScope.Trojan.Zbot.2312", "update": "20190604"}, "ALYac": {"detected": true, "version": "1.1.1.5", "result": "Gen:Variant.Ursu.368581", "update": "20190604"}, "MAX": {"detected": true, "version": "2018.9.12.1", "result": "malware (ai score=94)", "update": "20190605"}, "Malwarebytes": {"detected": true, "version": "2.1.1.1115", "result": "Backdoor.Tofsee", "update": "20190604"}, "Zoner": {"detected": false, "version": "1.0", "result": null, "update": "20190604"}, "ESET-NOD32": {"detected": true, "version": "19469", "result": "a variant of Win32/Kryptik.GOPY", "update": "20190604"}, "TrendMicro-HouseCall": {"detected": true, "version": "10.0.0.1040", "result": "Trojan.Win32.ELENOOKA.SM.hp", "update": "20190604"}, "Rising": {"detected": true, "version": "25.0.0.24", "result": "Backdoor.Tofsee!8.1E9 (CLOUD)", "update": "20190604"}, "Yandex": {"detected": true, "version": "5.5.2.24", "result": "Backdoor.Tofsee!jI9Ugm/H1bY", "update": "20190604"}, "Ikarus": {"detected": true, "version": "0.1.5.2", "result": "Trojan.Win32.Tofsee", "update": "20190604"}, "eGambit": {"detected": true, "version": "v4.3.6", "result": "Unsafe.AI_Score_94%", "update": "20190605"}, "GData": {"detected": true, "version": "A:25.22251B:25.15242", "result": "Gen:Variant.Ursu.368581", "update": "20190604"}, "AVG": {"detected": true, "version": "18.4.3895.0", "result": "Win32:ReposFxg-F [Trj]", "update": "20190604"}, "Cybereason": {"detected": true, "version": "1.2.449", "result": "malicious.d3792c", "update": "20190417"}, "Panda": {"detected": true, "version": "4.6.4.2", "result": "Trj/GdSda.A", "update": "20190604"}, "CrowdStrike": {"detected": true, "version": "1.0", "result": "win/malicious_confidence_100% (W)", "update": "20190212"}, "Qihoo-360": {"detected": true, "version": "1.0.0.1120", "result": "Win32/Trojan.451", "update": "20190605"}}, "scan_id": "ccdef4b25564f424772317356e27e6aa51976d2805594024b30f7b852f1ccf34-1559693719", "sha1": "0ff29329f16f7db036d345554ddec2fe5c85d4f7", "resource": "ccdef4b25564f424772317356e27e6aa51976d2805594024b30f7b852f1ccf34", "response_code": 1, "scan_date": "2019-06-05 00:15:19", "permalink": "https://www.virustotal.com/gui/file/ccdef4b25564f424772317356e27e6aa51976d2805594024b30f7b852f1ccf34/detection/f-ccdef4b25564f424772317356e27e6aa51976d2805594024b30f7b852f1ccf34-1559693719", "verbose_msg": "Scan finished, information embedded", "total": 71, "positives": 57, "sha256": "ccdef4b25564f424772317356e27e6aa51976d2805594024b30f7b852f1ccf34", "md5": "9f97a5dd3792cdcc69fe49b219be31fc"}}, "<class 'lib.class_helper.HTTP'>": {"https://www.google.com": {"meta": {"url_info": {"url": "https://www.google.com/", "id": "d0e196a0c25d35dd0a84593cbae0f38333aa58529936444ea26453eab28dfc86"}}, "data": {"attributes": {"date": 1686521149, "status": "completed", "stats": {"harmless": 73, "malicious": 1, "suspicious": 0, "undetected": 15, "timeout": 0}, "results": {"Bkav": {"category": "undetected", "result": "unrated", "method": "blacklist", "engine_name": "Bkav"}, "CMC Threat Intelligence": {"category": "malicious", "result": "malicious", "method": "blacklist", "engine_name": "CMC Threat Intelligence"}, "Snort IP sample list": {"category": "harmless", "result": "clean", "method": "blacklist", "engine_name": "Snort IP sample list"}, "VX Vault": {"category": "harmless", "result": "clean", "method": "blacklist", "engine_name": "VX Vault"}, "ViriBack": {"category": "harmless", "result": "clean", "method": "blacklist", "engine_name": "ViriBack"}, "PhishLabs": {"category": "harmless", "result": "clean", "method": "blacklist", "engine_name": "PhishLabs"}, "K7AntiVirus": {"category": "harmless", "result": "clean", "method": "blacklist", "engine_name": "K7AntiVirus"}, "CINS Army": {"category": "harmless", "result": "clean", "method": "blacklist", "engine_name": "CINS Army"}, "Quttera": {"category": "harmless", "result": "clean", "method": "blacklist", "engine_name": "Quttera"}, "BlockList": {"category": "harmless", "result": "clean", "method": "blacklist", "engine_name": "BlockList"}, "PrecisionSec": {"category": "undetected", "result": "unrated", "method": "blacklist", "engine_name": "PrecisionSec"}, "OpenPhish": {"category": "harmless", "result": "clean", "method": "blacklist", "engine_name": "OpenPhish"}, "0xSI_f33d": {"category": "undetected", "result": "unrated", "method": "blacklist", "engine_name": "0xSI_f33d"}, "Feodo Tracker": {"category": "harmless", "result": "clean", "method": "blacklist", "engine_name": "Feodo Tracker"}, "ArcSight Threat Intelligence": {"category": "undetected", "result": "unrated", "method": "blacklist", "engine_name": "ArcSight Threat Intelligence"}, "Scantitan": {"category": "harmless", "result": "clean", "method": "blacklist", "engine_name": "Scantitan"}, "AlienVault": {"category": "harmless", "result": "clean", "method": "blacklist", "engine_name": "AlienVault"}, "Sophos": {"category": "harmless", "result": "clean", "method": "blacklist", "engine_name": "Sophos"}, "Phishtank": {"category": "harmless", "result": "clean", "method": "blacklist", "engine_name": "Phishtank"}, "Cyan": {"category": "undetected", "result": "unrated", "method": "blacklist", "engine_name": "Cyan"}, "Spam404": {"category": "harmless", "result": "clean", "method": "blacklist", "engine_name": "Spam404"}, "SecureBrain": {"category": "harmless", "result": "clean", "method": "blacklist", "engine_name": "SecureBrain"}, "CRDF": {"category": "harmless", "result": "clean", "method": "blacklist", "engine_name": "CRDF"}, "Rising": {"category": "harmless", "result": "clean", "method": "blacklist", "engine_name": "Rising"}, "Fortinet": {"category": "harmless", "result": "clean", "method": "blacklist", "engine_name": "Fortinet"}, "alphaMountain.ai": {"category": "harmless", "result": "clean", "method": "blacklist", "engine_name": "alphaMountain.ai"}, "Lionic": {"category": "harmless", "result": "clean", "method": "blacklist", "engine_name": "Lionic"}, "Cyble": {"category": "harmless", "result": "clean", "method": "blacklist", "engine_name": "Cyble"}, "Seclookup": {"category": "harmless", "result": "clean", "method": "blacklist", "engine_name": "Seclookup"}, "Xcitium Verdict Cloud": {"category": "harmless", "result": "clean", "method": "blacklist", "engine_name": "Xcitium Verdict Cloud"}, "Artists Against 419": {"category": "harmless", "result": "clean", "method": "blacklist", "engine_name": "Artists Against 419"}, "Google Safebrowsing": {"category": "harmless", "result": "clean", "method": "blacklist", "engine_name": "Google Safebrowsing"}, "SafeToOpen": {"category": "undetected", "result": "unrated", "method": "blacklist", "engine_name": "SafeToOpen"}, "ADMINUSLabs": {"category": "harmless", "result": "clean", "method": "blacklist", "engine_name": "ADMINUSLabs"}, "ESTsecurity": {"category": "harmless", "result": "clean", "method": "blacklist", "engine_name": "ESTsecurity"}, "Juniper Networks": {"category": "harmless", "result": "clean", "method": "blacklist", "engine_name": "Juniper Networks"}, "Heimdal Security": {"category": "harmless", "result": "clean", "method": "blacklist", "engine_name": "Heimdal Security"}, "AutoShun": {"category": "undetected", "result": "unrated", "method": "blacklist", "engine_name": "AutoShun"}, "Trustwave": {"category": "harmless", "result": "clean", "method": "blacklist", "engine_name": "Trustwave"}, "AICC (MONITORAPP)": {"category": "harmless", "result": "clean", "method": "blacklist", "engine_name": "AICC (MONITORAPP)"}, "CyRadar": {"category": "harmless", "result": "clean", "method": "blacklist", "engine_name": "CyRadar"}, "Dr.Web": {"category": "harmless", "result": "clean", "method": "blacklist", "engine_name": "Dr.Web"}, "Emsisoft": {"category": "harmless", "result": "clean", "method": "blacklist", "engine_name": "Emsisoft"}, "Abusix": {"category": "harmless", "result": "clean", "method": "blacklist", "engine_name": "Abusix"}, "Webroot": {"category": "harmless", "result": "clean", "method": "blacklist", "engine_name": "Webroot"}, "Avira": {"category": "harmless", "result": "clean", "method": "blacklist", "engine_name": "Avira"}, "securolytics": {"category": "harmless", "result": "clean", "method": "blacklist", "engine_name": "securolytics"}, "Antiy-AVL": {"category": "harmless", "result": "clean", "method": "blacklist", "engine_name": "Antiy-AVL"}, "AlphaSOC": {"category": "undetected", "result": "unrated", "method": "blacklist", "engine_name": "AlphaSOC"}, "Acronis": {"category": "harmless", "result": "clean", "method": "blacklist", "engine_name": "Acronis"}, "Quick Heal": {"category": "harmless", "result": "clean", "method": "blacklist", "engine_name": "Quick Heal"}, "URLQuery": {"category": "harmless", "result": "clean", "method": "blacklist", "engine_name": "URLQuery"}, "Viettel Threat Intelligence": {"category": "harmless", "result": "clean", "method": "blacklist", "engine_name": "Viettel Threat Intelligence"}, "DNS8": {"category": "harmless", "result": "clean", "method": "blacklist", "engine_name": "DNS8"}, "benkow.cc": {"category": "harmless", "result": "clean", "method": "blacklist", "engine_name": "benkow.cc"}, "EmergingThreats": {"category": "harmless", "result": "clean", "method": "blacklist", "engine_name": "EmergingThreats"}, "Chong Lua Dao": {"category": "harmless", "result": "clean", "method": "blacklist", "engine_name": "Chong Lua Dao"}, "Yandex Safebrowsing": {"category": "harmless", "result": "clean", "method": "blacklist", "engine_name": "Yandex Safebrowsing"}, "Lumu": {"category": "undetected", "result": "unrated", "method": "blacklist", "engine_name": "Lumu"}, "Kaspersky": {"category": "harmless", "result": "clean", "method": "blacklist", "engine_name": "Kaspersky"}, "Sucuri SiteCheck": {"category": "harmless", "result": "clean", "method": "blacklist", "engine_name": "Sucuri SiteCheck"}, "desenmascara.me": {"category": "harmless", "result": "clean", "method": "blacklist", "engine_name": "desenmascara.me"}, "CrowdSec": {"category": "undetected", "result": "unrated", "method": "blacklist", "engine_name": "CrowdSec"}, "Cluster25": {"category": "undetected", "result": "unrated", "method": "blacklist", "engine_name": "Cluster25"}, "URLhaus": {"category": "harmless", "result": "clean", "method": "blacklist", "engine_name": "URLhaus"}, "PREBYTES": {"category": "harmless", "result": "clean", "method": "blacklist", "engine_name": "PREBYTES"}, "StopForumSpam": {"category": "harmless", "result": "clean", "method": "blacklist", "engine_name": "StopForumSpam"}, "Blueliv": {"category": "harmless", "result": "clean", "method": "blacklist", "engine_name": "Blueliv"}, "Netcraft": {"category": "undetected", "result": "unrated", "method": "blacklist", "engine_name": "Netcraft"}, "ZeroCERT": {"category": "harmless", "result": "clean", "method": "blacklist", "engine_name": "ZeroCERT"}, "Phishing Database": {"category": "harmless", "result": "clean", "method": "blacklist", "engine_name": "Phishing Database"}, "MalwarePatrol": {"category": "harmless", "result": "clean", "method": "blacklist", "engine_name": "MalwarePatrol"}, "Sangfor": {"category": "harmless", "result": "clean", "method": "blacklist", "engine_name": "Sangfor"}, "IPsum": {"category": "harmless", "result": "clean", "method": "blacklist", "engine_name": "IPsum"}, "Malwared": {"category": "harmless", "result": "clean", "method": "blacklist", "engine_name": "Malwared"}, "BitDefender": {"category": "harmless", "result": "clean", "method": "blacklist", "engine_name": "BitDefender"}, "GreenSnow": {"category": "harmless", "result": "clean", "method": "blacklist", "engine_name": "GreenSnow"}, "G-Data": {"category": "harmless", "result": "clean", "method": "blacklist", "engine_name": "G-Data"}, "VIPRE": {"category": "undetected", "result": "unrated", "method": "blacklist", "engine_name": "VIPRE"}, "SCUMWARE.org": {"category": "harmless", "result": "clean", "method": "blacklist", "engine_name": "SCUMWARE.org"}, "PhishFort": {"category": "undetected", "result": "unrated", "method": "blacklist", "engine_name": "PhishFort"}, "malwares.com URL checker": {"category": "harmless", "result": "clean", "method": "blacklist", "engine_name": "malwares.com URL checker"}, "Forcepoint ThreatSeeker": {"category": "harmless", "result": "clean", "method": "blacklist", "engine_name": "Forcepoint ThreatSeeker"}, "Criminal IP": {"category": "undetected", "result": "unrated", "method": "blacklist", "engine_name": "Criminal IP"}, "Certego": {"category": "harmless", "result": "clean", "method": "blacklist", "engine_name": "Certego"}, "ESET": {"category": "harmless", "result": "clean", "method": "blacklist", "engine_name": "ESET"}, "Threatsourcing": {"category": "harmless", "result": "clean", "method": "blacklist", "engine_name": "Threatsourcing"}, "ThreatHive": {"category": "harmless", "result": "clean", "method": "blacklist", "engine_name": "ThreatHive"}, "Bfore.Ai PreCrime": {"category": "harmless", "result": "clean", "method": "blacklist", "engine_name": "Bfore.Ai PreCrime"}}}, "type": "analysis", "id": "u-d0e196a0c25d35dd0a84593cbae0f38333aa58529936444ea26453eab28dfc86-1686521149", "links": {"item": "https://www.virustotal.com/api/v3/urls/d0e196a0c25d35dd0a84593cbae0f38333aa58529936444ea26453eab28dfc86", "self": "https://www.virustotal.com/api/v3/analyses/u-d0e196a0c25d35dd0a84593cbae0f38333aa58529936444ea26453eab28dfc86-1686521149"}}}}, "<class 'ipaddress.IPv4Address'>": {"1.1.1.1": {"data": {"attributes": {"jarm": "27d3ed3ed0003ed1dc42d43d00041d6183ff1bfae51ebd88d70384363d525c", "network": "1.1.1.0/24", "last_https_certificate_date": 1686503647, "tags": ["suspicious-udp"], "last_analysis_date": 1686503344, "as_owner": "CLOUDFLARENET", "last_analysis_stats": {"harmless": 66, "malicious": 4, "suspicious": 0, "undetected": 17, "timeout": 0}, "whois_date": 1684184299, "last_analysis_results": {"Bkav": {"category": "undetected", "result": "unrated", "method": "blacklist", "engine_name": "Bkav"}, "CMC Threat Intelligence": {"category": "harmless", "result": "clean", "method": "blacklist", "engine_name": "CMC Threat Intelligence"}, "Snort IP sample list": {"category": "harmless", "result": "clean", "method": "blacklist", "engine_name": "Snort IP sample list"}, "0xSI_f33d": {"category": "undetected", "result": "unrated", "method": "blacklist", "engine_name": "0xSI_f33d"}, "ViriBack": {"category": "harmless", "result": "clean", "method": "blacklist", "engine_name": "ViriBack"}, "PhishLabs": {"category": "undetected", "result": "unrated", "method": "blacklist", "engine_name": "PhishLabs"}, "K7AntiVirus": {"category": "harmless", "result": "clean", "method": "blacklist", "engine_name": "K7AntiVirus"}, "CINS Army": {"category": "harmless", "result": "clean", "method": "blacklist", "engine_name": "CINS Army"}, "Quttera": {"category": "harmless", "result": "clean", "method": "blacklist", "engine_name": "Quttera"}, "PrecisionSec": {"category": "undetected", "result": "unrated", "method": "blacklist", "engine_name": "PrecisionSec"}, "OpenPhish": {"category": "harmless", "result": "clean", "method": "blacklist", "engine_name": "OpenPhish"}, "VX Vault": {"category": "harmless", "result": "clean", "method": "blacklist", "engine_name": "VX Vault"}, "ArcSight Threat Intelligence": {"category": "undetected", "result": "unrated", "method": "blacklist", "engine_name": "ArcSight Threat Intelligence"}, "Scantitan": {"category": "harmless", "result": "clean", "method": "blacklist", "engine_name": "Scantitan"}, "AlienVault": {"category": "harmless", "result": "clean", "method": "blacklist", "engine_name": "AlienVault"}, "Sophos": {"category": "harmless", "result": "clean", "method": "blacklist", "engine_name": "Sophos"}, "Phishtank": {"category": "harmless", "result": "clean", "method": "blacklist", "engine_name": "Phishtank"}, "Cyan": {"category": "undetected", "result": "unrated", "method": "blacklist", "engine_name": "Cyan"}, "Spam404": {"category": "harmless", "result": "clean", "method": "blacklist", "engine_name": "Spam404"}, "SecureBrain": {"category": "harmless", "result": "clean", "method": "blacklist", "engine_name": "SecureBrain"}, "CRDF": {"category": "harmless", "result": "clean", "method": "blacklist", "engine_name": "CRDF"}, "Fortinet": {"category": "harmless", "result": "clean", "method": "blacklist", "engine_name": "Fortinet"}, "alphaMountain.ai": {"category": "harmless", "result": "clean", "method": "blacklist", "engine_name": "alphaMountain.ai"}, "Lionic": {"category": "harmless", "result": "clean", "method": "blacklist", "engine_name": "Lionic"}, "Cyble": {"category": "harmless", "result": "clean", "method": "blacklist", "engine_name": "Cyble"}, "Seclookup": {"category": "harmless", "result": "clean", "method": "blacklist", "engine_name": "Seclookup"}, "Xcitium Verdict Cloud": {"category": "malicious", "result": "phishing", "method": "blacklist", "engine_name": "Xcitium Verdict Cloud"}, "Google Safebrowsing": {"category": "harmless", "result": "clean", "method": "blacklist", "engine_name": "Google Safebrowsing"}, "SafeToOpen": {"category": "undetected", "result": "unrated", "method": "blacklist", "engine_name": "SafeToOpen"}, "ADMINUSLabs": {"category": "harmless", "result": "clean", "method": "blacklist", "engine_name": "ADMINUSLabs"}, "ESTsecurity": {"category": "harmless", "result": "clean", "method": "blacklist", "engine_name": "ESTsecurity"}, "Juniper Networks": {"category": "harmless", "result": "clean", "method": "blacklist", "engine_name": "Juniper Networks"}, "Heimdal Security": {"category": "harmless", "result": "clean", "method": "blacklist", "engine_name": "Heimdal Security"}, "AutoShun": {"category": "undetected", "result": "unrated", "method": "blacklist", "engine_name": "AutoShun"}, "Trustwave": {"category": "harmless", "result": "clean", "method": "blacklist", "engine_name": "Trustwave"}, "AICC (MONITORAPP)": {"category": "harmless", "result": "clean", "method": "blacklist", "engine_name": "AICC (MONITORAPP)"}, "CyRadar": {"category": "malicious", "result": "malicious", "method": "blacklist", "engine_name": "CyRadar"}, "Dr.Web": {"category": "harmless", "result": "clean", "method": "blacklist", "engine_name": "Dr.Web"}, "Emsisoft": {"category": "harmless", "result": "clean", "method": "blacklist", "engine_name": "Emsisoft"}, "Abusix": {"category": "harmless", "result": "clean", "method": "blacklist", "engine_name": "Abusix"}, "Webroot": {"category": "harmless", "result": "clean", "method": "blacklist", "engine_name": "Webroot"}, "Avira": {"category": "harmless", "result": "clean", "method": "blacklist", "engine_name": "Avira"}, "securolytics": {"category": "harmless", "result": "clean", "method": "blacklist", "engine_name": "securolytics"}, "Antiy-AVL": {"category": "harmless", "result": "clean", "method": "blacklist", "engine_name": "Antiy-AVL"}, "AlphaSOC": {"category": "undetected", "result": "unrated", "method": "blacklist", "engine_name": "AlphaSOC"}, "Acronis": {"category": "harmless", "result": "clean", "method": "blacklist", "engine_name": "Acronis"}, "Quick Heal": {"category": "harmless", "result": "clean", "method": "blacklist", "engine_name": "Quick Heal"}, "URLQuery": {"category": "undetected", "result": "unrated", "method": "blacklist", "engine_name": "URLQuery"}, "Viettel Threat Intelligence": {"category": "harmless", "result": "clean", "method": "blacklist", "engine_name": "Viettel Threat Intelligence"}, "DNS8": {"category": "harmless", "result": "clean", "method": "blacklist", "engine_name": "DNS8"}, "benkow.cc": {"category": "harmless", "result": "clean", "method": "blacklist", "engine_name": "benkow.cc"}, "EmergingThreats": {"category": "harmless", "result": "clean", "method": "blacklist", "engine_name": "EmergingThreats"}, "Chong Lua Dao": {"category": "harmless", "result": "clean", "method": "blacklist", "engine_name": "Chong Lua Dao"}, "Yandex Safebrowsing": {"category": "harmless", "result": "clean", "method": "blacklist", "engine_name": "Yandex Safebrowsing"}, "Lumu": {"category": "undetected", "result": "unrated", "method": "blacklist", "engine_name": "Lumu"}, "zvelo": {"category": "harmless", "result": "clean", "method": "blacklist", "engine_name": "zvelo"}, "Kaspersky": {"category": "harmless", "result": "clean", "method": "blacklist", "engine_name": "Kaspersky"}, "Segasec": {"category": "undetected", "result": "unrated", "method": "blacklist", "engine_name": "Segasec"}, "Sucuri SiteCheck": {"category": "harmless", "result": "clean", "method": "blacklist", "engine_name": "Sucuri SiteCheck"}, "desenmascara.me": {"category": "harmless", "result": "clean", "method": "blacklist", "engine_name": "desenmascara.me"}, "CrowdSec": {"category": "malicious", "result": "malicious", "method": "blacklist", "engine_name": "CrowdSec"}, "Cluster25": {"category": "undetected", "result": "unrated", "method": "blacklist", "engine_name": "Cluster25"}, "URLhaus": {"category": "harmless", "result": "clean", "method": "blacklist", "engine_name": "URLhaus"}, "PREBYTES": {"category": "harmless", "result": "clean", "method": "blacklist", "engine_name": "PREBYTES"}, "StopForumSpam": {"category": "harmless", "result": "clean", "method": "blacklist", "engine_name": "StopForumSpam"}, "Blueliv": {"category": "malicious", "result": "malicious", "method": "blacklist", "engine_name": "Blueliv"}, "Netcraft": {"category": "undetected", "result": "unrated", "method": "blacklist", "engine_name": "Netcraft"}, "ZeroCERT": {"category": "harmless", "result": "clean", "method": "blacklist", "engine_name": "ZeroCERT"}, "Phishing Database": {"category": "harmless", "result": "clean", "method": "blacklist", "engine_name": "Phishing Database"}, "MalwarePatrol": {"category": "harmless", "result": "clean", "method": "blacklist", "engine_name": "MalwarePatrol"}, "IPsum": {"category": "harmless", "result": "clean", "method": "blacklist", "engine_name": "IPsum"}, "Malwared": {"category": "harmless", "result": "clean", "method": "blacklist", "engine_name": "Malwared"}, "BitDefender": {"category": "harmless", "result": "clean", "method": "blacklist", "engine_name": "BitDefender"}, "GreenSnow": {"category": "harmless", "result": "clean", "method": "blacklist", "engine_name": "GreenSnow"}, "G-Data": {"category": "harmless", "result": "clean", "method": "blacklist", "engine_name": "G-Data"}, "VIPRE": {"category": "undetected", "result": "unrated", "method": "blacklist", "engine_name": "VIPRE"}, "SCUMWARE.org": {"category": "harmless", "result": "clean", "method": "blacklist", "engine_name": "SCUMWARE.org"}, "PhishFort": {"category": "undetected", "result": "unrated", "method": "blacklist", "engine_name": "PhishFort"}, "malwares.com URL checker": {"category": "harmless", "result": "clean", "method": "blacklist", "engine_name": "malwares.com URL checker"}, "Forcepoint ThreatSeeker": {"category": "harmless", "result": "clean", "method": "blacklist", "engine_name": "Forcepoint ThreatSeeker"}, "Criminal IP": {"category": "harmless", "result": "clean", "method": "blacklist", "engine_name": "Criminal IP"}, "Certego": {"category": "harmless", "result": "clean", "method": "blacklist", "engine_name": "Certego"}, "ESET": {"category": "harmless", "result": "clean", "method": "blacklist", "engine_name": "ESET"}, "Threatsourcing": {"category": "harmless", "result": "clean", "method": "blacklist", "engine_name": "Threatsourcing"}, "ThreatHive": {"category": "harmless", "result": "clean", "method": "blacklist", "engine_name": "ThreatHive"}, "Bfore.Ai PreCrime": {"category": "harmless", "result": "clean", "method": "blacklist", "engine_name": "Bfore.Ai PreCrime"}}, "reputation": 92, "last_modification_date": 1686517915, "total_votes": {"harmless": 77, "malicious": 13}, "last_https_certificate": {"public_key": {"algorithm": "EC", "ec": {"oid": "secp256r1", "pub": "3059301306072a8648ce3d020106082a8648ce3d03010703420004f1603c98db04431c75fc8bdf7013598ff1ce586105a071f980b4c943e983890dfe22d6aa098ed34fe47fa62718179963568c3b47b8e7ea20b13059158d70a11b"}}, "thumbprint_sha256": "98ce6111a81057e7d8d4fdf470278b2fb77781c4bb79bfb31fd31047c388d5a3", "thumbprint": "17cfe81b0c957357bd6bcd282673003ea72ef216", "subject": {"C": "US", "ST": "California", "L": "San Francisco", "O": "Cloudflare, Inc.", "CN": "cloudflare-dns.com"}, "validity": {"not_after": "2024-01-11 23:59:59", "not_before": "2023-01-12 00:00:00"}, "version": "V3", "extensions": {"certificate_policies": ["2.23.140.1.2.2"], "extended_key_usage": ["serverAuth", "clientAuth"], "authority_key_identifier": {"keyid": "0abc0829178ca5396d7a0ece33c72eb3edfbc37a"}, "subject_alternative_name": ["cloudflare-dns.com", "*.cloudflare-dns.com", "one.one.one.one", "1.0.0.1", "1.1.1.1", "162.159.36.1", "162.159.46.1", "2606:4700:4700::1001", "2606:4700:4700::1111", "2606:4700:4700::64", "2606:4700:4700::6400"], "ca_information_access": {"CA Issuers": "http://cacerts.digicert.com/DigiCertTLSHybridECCSHA3842020CA1-1.crt", "OCSP": "http://ocsp.digicert.com"}, "subject_key_identifier": "64bad8d7fb54218708f3b28266f99e5f4b7004f2", "crl_distribution_points": ["http://crl3.digicert.com/DigiCertTLSHybridECCSHA3842020CA1-1.crl", "http://crl4.digicert.com/DigiCertTLSHybridECCSHA3842020CA1-1.crl"], "key_usage": ["digitalSignature"], "1.3.6.1.4.1.11129.2.4.2": "048201690167007500eecdd064d5db1acec55cb79db4cd13a23287467cbcecde", "CA": false}, "cert_signature": {"signature_algorithm": "1.2.840.10045.4.3.3", "signature": "306402303ff8961ba59ad14f007438ef6d43b15dd23a5a0417c159e0fd6aecd86dcfd823d7c838bccb80f9db75df2180dd637290023034b7498beb6240360a4231ddf2ee83ab333d35bbf15055e975f265eaf8f02411807a4bef4124ec6319c2862045ed3318"}, "serial_number": "3c26a465bd5ed68de8f66f975ce2e5f", "issuer": {"C": "US", "CN": "DigiCert TLS Hybrid ECC SHA384 2020 CA1", "O": "DigiCert Inc"}, "size": 1529}, "asn": 13335, "whois": "Domain Name: one.one\r\nRegistry Domain ID: DB8D9612E99A84235AF9133FBE4EB27D5-ARI\r\nRegistrar WHOIS Server:\r\nRegistrar URL:\r\nUpdated Date: 2022-07-04T12:15:45Z\r\nCreation Date: 2015-05-20T12:15:44Z\r\nRegistry Expiry Date: 2023-05-20T12:15:44Z\r\nRegistrar: One.com A/S - ONE\r\nRegistrar IANA ID: 9998\r\nRegistrar Abuse Contact Email:\r\nRegistrar Abuse Contact Phone:\r\nDomain Status: ok https://icann.org/epp#ok\r\nRegistry Registrant ID: REDACTED FOR PRIVACY\r\nRegistrant Name: REDACTED FOR PRIVACY\r\nRegistrant Organization: One.com A/S\r\nRegistrant Street: REDACTED FOR PRIVACY\r\nRegistrant Street: REDACTED FOR PRIVACY\r\nRegistrant Street: REDACTED FOR PRIVACY\r\nRegistrant City: REDACTED FOR PRIVACY\r\nRegistrant State/Province:\r\nRegistrant Postal Code: REDACTED FOR PRIVACY\r\nRegistrant Country: dk\r\nRegistrant Phone: REDACTED FOR PRIVACY\r\nRegistrant Phone Ext: REDACTED FOR PRIVACY\r\nRegistrant Fax: REDACTED FOR PRIVACY\r\nRegistrant Fax Ext: REDACTED FOR PRIVACY\r\nRegistrant Email: Please query the RDDS service of the Registrar of Record identified in this output for information on how to contact the Registrant, Admin, or Tech contact of the queried domain name.\r\nRegistry Admin ID: REDACTED FOR PRIVACY\r\nAdmin Name: REDACTED FOR PRIVACY\r\nAdmin Organization: REDACTED FOR PRIVACY\r\nAdmin Street: REDACTED FOR PRIVACY\r\nAdmin Street: REDACTED FOR PRIVACY\r\nAdmin Street: REDACTED FOR PRIVACY\r\nAdmin City: REDACTED FOR PRIVACY\r\nAdmin State/Province: REDACTED FOR PRIVACY\r\nAdmin Postal Code: REDACTED FOR PRIVACY\r\nAdmin Country: REDACTED FOR PRIVACY\r\nAdmin Phone: REDACTED FOR PRIVACY\r\nAdmin Phone Ext: REDACTED FOR PRIVACY\r\nAdmin Fax: REDACTED FOR PRIVACY\r\nAdmin Fax Ext: REDACTED FOR PRIVACY\r\nAdmin Email: Please query the RDDS service of the Registrar of Record identified in this output for information on how to contact the Registrant, Admin, or Tech contact of the queried domain name.\r\nRegistry Tech ID: REDACTED FOR PRIVACY\r\nTech Name: REDACTED FOR PRIVACY\r\nTech Organization: REDACTED FOR PRIVACY\r\nTech Street: REDACTED FOR PRIVACY\r\nTech Street: REDACTED FOR PRIVACY\r\nTech Street: REDACTED FOR PRIVACY\r\nTech City: REDACTED FOR PRIVACY\r\nTech State/Province: REDACTED FOR PRIVACY\r\nTech Postal Code: REDACTED FOR PRIVACY\r\nTech Country: REDACTED FOR PRIVACY\r\nTech Phone: REDACTED FOR PRIVACY\r\nTech Phone Ext: REDACTED FOR PRIVACY\r\nTech Fax: REDACTED FOR PRIVACY\r\nTech Fax Ext: REDACTED FOR PRIVACY\r\nTech Email: Please query the RDDS service of the Registrar of Record identified in this output for information on how to contact the Registrant, Admin, or Tech contact of the queried domain name.\r\nName Server: a.b-one-dns.net\r\nName Server: b.b-one-dns.net\r\nDNSSEC: signedDelegation\r\nURL of the ICANN Whois Inaccuracy Complaint Form: https://www.icann.org/wicf/\r\n>>> Last update of WHOIS database: 2023-05-15T20:58:18Z <<<\r\n\r\nFor more information on Whois status codes, please visit https://icann.org/epp\r\n\r\nThe Service is provided so that you may look up certain information in relation to domain names that we store in our database.\r\n\r\nUse of the Service is subject to our policies, in particular you should familiarise yourself with our Acceptable Use Policy and our Privacy Policy.\r\n\r\nThe information provided by this Service is 'as is' and we make no guarantee of it its accuracy.\r\n\r\nYou agree that by your use of the Service you will not use the information provided by us in a way which is:\r\n* inconsistent with any applicable laws,\r\n* inconsistent with any policy issued by us,\r\n* to generate, distribute, or facilitate unsolicited mass email, promotions, advertisings or other solicitations, or\r\n* to enable high volume, automated, electronic processes that apply to the Service.\r\n\r\nYou acknowledge that:\r\n* a response from the Service that a domain name is 'available', does not guarantee that is able to be registered,\r\n* we may restrict, suspend or terminate your access to the Service at any time, and\r\n* the copying, compilation, repackaging, dissemination or other use of the information provided by the Service is not permitted, without our express written consent.\r\n\r\nThis information has been prepared and published in order to represent administrative and technical management of the TLD.\r\n\r\nWe may discontinue or amend any part or the whole of these Terms of Service from time to time at our absolute discretion.\r\n"}, "type": "ip_address", "id": "1.1.1.1", "links": {"self": "https://www.virustotal.com/api/v3/ip_addresses/1.1.1.1"}}}}, "<class 'lib.class_helper.DNSQuery'>": {"www.google.com": {"data": {"attributes": {"last_dns_records": [{"type": "A", "value": "142.250.203.100", "ttl": 300}, {"type": "AAAA", "value": "2a00:1450:400a:808::2004", "ttl": 300}], "jarm": "27d40d40d29d40d1dc42d43d00041d4689ee210389f4f6b4b5b1b93f92252d", "whois": "Admin Country: US\nAdmin Organization: Google LLC\nAdmin State/Province: CA\nCreation Date: 1997-09-15T04:00:00Z\nCreation Date: 1997-09-15T07:00:00+0000\nDNSSEC: unsigned\nDomain Name: GOOGLE.COM\nDomain Name: google.com\nDomain Status: clientDeleteProhibited (https://www.icann.org/epp#clientDeleteProhibited)\nDomain Status: clientDeleteProhibited https://icann.org/epp#clientDeleteProhibited\nDomain Status: clientTransferProhibited (https://www.icann.org/epp#clientTransferProhibited)\nDomain Status: clientTransferProhibited https://icann.org/epp#clientTransferProhibited\nDomain Status: clientUpdateProhibited (https://www.icann.org/epp#clientUpdateProhibited)\nDomain Status: clientUpdateProhibited https://icann.org/epp#clientUpdateProhibited\nDomain Status: serverDeleteProhibited (https://www.icann.org/epp#serverDeleteProhibited)\nDomain Status: serverDeleteProhibited https://icann.org/epp#serverDeleteProhibited\nDomain Status: serverTransferProhibited (https://www.icann.org/epp#serverTransferProhibited)\nDomain Status: serverTransferProhibited https://icann.org/epp#serverTransferProhibited\nDomain Status: serverUpdateProhibited (https://www.icann.org/epp#serverUpdateProhibited)\nDomain Status: serverUpdateProhibited https://icann.org/epp#serverUpdateProhibited\nName Server: NS1.GOOGLE.COM\nName Server: NS2.GOOGLE.COM\nName Server: NS3.GOOGLE.COM\nName Server: NS4.GOOGLE.COM\nName Server: ns1.google.com\nName Server: ns2.google.com\nName Server: ns3.google.com\nName Server: ns4.google.com\nRegistrant Country: US\nRegistrant Email: ca4484b9e50182bds@\nRegistrant Organization: 3307059bbb3149c4\nRegistrant State/Province: b1952dfc047df18a\nRegistrar Abuse Contact Email: abusecomplaints@markmonitor.com\nRegistrar Abuse Contact Phone: +1.2086851750\nRegistrar IANA ID: 292\nRegistrar Registration Expiration Date: 2028-09-13T07:00:00+0000\nRegistrar URL: http://www.markmonitor.com\nRegistrar WHOIS Server: whois.markmonitor.com\nRegistrar: MarkMonitor Inc.\nRegistrar: MarkMonitor, Inc.\nRegistry Domain ID: 2138514_DOMAIN_COM-VRSN\nRegistry Expiry Date: 2028-09-14T04:00:00Z\nTech Country: US\nTech Organization: Google LLC\nTech State/Province: CA\nUpdated Date: 2019-09-09T15:39:04+0000\nUpdated Date: 2019-09-09T15:39:04Z", "last_https_certificate_date": 1686441623, "tags": [], "popularity_ranks": {"Cisco Umbrella": {"timestamp": 1686502681, "rank": 3}}, "last_analysis_date": 1686441615, "last_dns_records_date": 1686441623, "last_analysis_stats": {"harmless": 70, "malicious": 1, "suspicious": 0, "undetected": 16, "timeout": 0}, "creation_date": 874306800, "reputation": 196, "registrar": "MarkMonitor Inc.", "last_analysis_results": {"Bkav": {"category": "undetected", "result": "unrated", "method": "blacklist", "engine_name": "Bkav"}, "CMC Threat Intelligence": {"category": "malicious", "result": "malicious", "method": "blacklist", "engine_name": "CMC Threat Intelligence"}, "Snort IP sample list": {"category": "harmless", "result": "clean", "method": "blacklist", "engine_name": "Snort IP sample list"}, "0xSI_f33d": {"category": "undetected", "result": "unrated", "method": "blacklist", "engine_name": "0xSI_f33d"}, "ViriBack": {"category": "harmless", "result": "clean", "method": "blacklist", "engine_name": "ViriBack"}, "PhishLabs": {"category": "harmless", "result": "clean", "method": "blacklist", "engine_name": "PhishLabs"}, "K7AntiVirus": {"category": "harmless", "result": "clean", "method": "blacklist", "engine_name": "K7AntiVirus"}, "CINS Army": {"category": "harmless", "result": "clean", "method": "blacklist", "engine_name": "CINS Army"}, "Quttera": {"category": "harmless", "result": "clean", "method": "blacklist", "engine_name": "Quttera"}, "PrecisionSec": {"category": "undetected", "result": "unrated", "method": "blacklist", "engine_name": "PrecisionSec"}, "OpenPhish": {"category": "harmless", "result": "clean", "method": "blacklist", "engine_name": "OpenPhish"}, "VX Vault": {"category": "harmless", "result": "clean", "method": "blacklist", "engine_name": "VX Vault"}, "ArcSight Threat Intelligence": {"category": "undetected", "result": "unrated", "method": "blacklist", "engine_name": "ArcSight Threat Intelligence"}, "Scantitan": {"category": "harmless", "result": "clean", "method": "blacklist", "engine_name": "Scantitan"}, "AlienVault": {"category": "harmless", "result": "clean", "method": "blacklist", "engine_name": "AlienVault"}, "Sophos": {"category": "harmless", "result": "clean", "method": "blacklist", "engine_name": "Sophos"}, "Phishtank": {"category": "harmless", "result": "clean", "method": "blacklist", "engine_name": "Phishtank"}, "Cyan": {"category": "undetected", "result": "unrated", "method": "blacklist", "engine_name": "Cyan"}, "Spam404": {"category": "harmless", "result": "clean", "method": "blacklist", "engine_name": "Spam404"}, "SecureBrain": {"category": "harmless", "result": "clean", "method": "blacklist", "engine_name": "SecureBrain"}, "CRDF": {"category": "harmless", "result": "clean", "method": "blacklist", "engine_name": "CRDF"}, "Fortinet": {"category": "harmless", "result": "clean", "method": "blacklist", "engine_name": "Fortinet"}, "alphaMountain.ai": {"category": "harmless", "result": "clean", "method": "blacklist", "engine_name": "alphaMountain.ai"}, "Lionic": {"category": "harmless", "result": "clean", "method": "blacklist", "engine_name": "Lionic"}, "Cyble": {"category": "harmless", "result": "clean", "method": "blacklist", "engine_name": "Cyble"}, "Seclookup": {"category": "harmless", "result": "clean", "method": "blacklist", "engine_name": "Seclookup"}, "Xcitium Verdict Cloud": {"category": "harmless", "result": "clean", "method": "blacklist", "engine_name": "Xcitium Verdict Cloud"}, "Google Safebrowsing": {"category": "harmless", "result": "clean", "method": "blacklist", "engine_name": "Google Safebrowsing"}, "SafeToOpen": {"category": "undetected", "result": "unrated", "method": "blacklist", "engine_name": "SafeToOpen"}, "ADMINUSLabs": {"category": "harmless", "result": "clean", "method": "blacklist", "engine_name": "ADMINUSLabs"}, "ESTsecurity": {"category": "harmless", "result": "clean", "method": "blacklist", "engine_name": "ESTsecurity"}, "Juniper Networks": {"category": "harmless", "result": "clean", "method": "blacklist", "engine_name": "Juniper Networks"}, "Heimdal Security": {"category": "harmless", "result": "clean", "method": "blacklist", "engine_name": "Heimdal Security"}, "AutoShun": {"category": "undetected", "result": "unrated", "method": "blacklist", "engine_name": "AutoShun"}, "Trustwave": {"category": "harmless", "result": "clean", "method": "blacklist", "engine_name": "Trustwave"}, "AICC (MONITORAPP)": {"category": "harmless", "result": "clean", "method": "blacklist", "engine_name": "AICC (MONITORAPP)"}, "CyRadar": {"category": "harmless", "result": "clean", "method": "blacklist", "engine_name": "CyRadar"}, "Dr.Web": {"category": "harmless", "result": "clean", "method": "blacklist", "engine_name": "Dr.Web"}, "Emsisoft": {"category": "harmless", "result": "clean", "method": "blacklist", "engine_name": "Emsisoft"}, "Abusix": {"category": "harmless", "result": "clean", "method": "blacklist", "engine_name": "Abusix"}, "Webroot": {"category": "harmless", "result": "clean", "method": "blacklist", "engine_name": "Webroot"}, "Avira": {"category": "harmless", "result": "clean", "method": "blacklist", "engine_name": "Avira"}, "securolytics": {"category": "harmless", "result": "clean", "method": "blacklist", "engine_name": "securolytics"}, "Antiy-AVL": {"category": "harmless", "result": "clean", "method": "blacklist", "engine_name": "Antiy-AVL"}, "AlphaSOC": {"category": "undetected", "result": "unrated", "method": "blacklist", "engine_name": "AlphaSOC"}, "Acronis": {"category": "harmless", "result": "clean", "method": "blacklist", "engine_name": "Acronis"}, "Quick Heal": {"category": "harmless", "result": "clean", "method": "blacklist", "engine_name": "Quick Heal"}, "URLQuery": {"category": "harmless", "result": "clean", "method": "blacklist", "engine_name": "URLQuery"}, "Viettel Threat Intelligence": {"category": "harmless", "result": "clean", "method": "blacklist", "engine_name": "Viettel Threat Intelligence"}, "DNS8": {"category": "harmless", "result": "clean", "method": "blacklist", "engine_name": "DNS8"}, "benkow.cc": {"category": "harmless", "result": "clean", "method": "blacklist", "engine_name": "benkow.cc"}, "EmergingThreats": {"category": "harmless", "result": "clean", "method": "blacklist", "engine_name": "EmergingThreats"}, "Chong Lua Dao": {"category": "harmless", "result": "clean", "method": "blacklist", "engine_name": "Chong Lua Dao"}, "Yandex Safebrowsing": {"category": "harmless", "result": "clean", "method": "blacklist", "engine_name": "Yandex Safebrowsing"}, "Lumu": {"category": "undetected", "result": "unrated", "method": "blacklist", "engine_name": "Lumu"}, "zvelo": {"category": "harmless", "result": "clean", "method": "blacklist", "engine_name": "zvelo"}, "Kaspersky": {"category": "harmless", "result": "clean", "method": "blacklist", "engine_name": "Kaspersky"}, "Segasec": {"category": "harmless", "result": "clean", "method": "blacklist", "engine_name": "Segasec"}, "Sucuri SiteCheck": {"category": "harmless", "result": "clean", "method": "blacklist", "engine_name": "Sucuri SiteCheck"}, "desenmascara.me": {"category": "harmless", "result": "clean", "method": "blacklist", "engine_name": "desenmascara.me"}, "CrowdSec": {"category": "undetected", "result": "unrated", "method": "blacklist", "engine_name": "CrowdSec"}, "Cluster25": {"category": "undetected", "result": "unrated", "method": "blacklist", "engine_name": "Cluster25"}, "URLhaus": {"category": "harmless", "result": "clean", "method": "blacklist", "engine_name": "URLhaus"}, "PREBYTES": {"category": "harmless", "result": "clean", "method": "blacklist", "engine_name": "PREBYTES"}, "StopForumSpam": {"category": "harmless", "result": "clean", "method": "blacklist", "engine_name": "StopForumSpam"}, "Blueliv": {"category": "harmless", "result": "clean", "method": "blacklist", "engine_name": "Blueliv"}, "Netcraft": {"category": "undetected", "result": "unrated", "method": "blacklist", "engine_name": "Netcraft"}, "ZeroCERT": {"category": "harmless", "result": "clean", "method": "blacklist", "engine_name": "ZeroCERT"}, "Phishing Database": {"category": "harmless", "result": "clean", "method": "blacklist", "engine_name": "Phishing Database"}, "MalwarePatrol": {"category": "harmless", "result": "clean", "method": "blacklist", "engine_name": "MalwarePatrol"}, "IPsum": {"category": "harmless", "result": "clean", "method": "blacklist", "engine_name": "IPsum"}, "Malwared": {"category": "harmless", "result": "clean", "method": "blacklist", "engine_name": "Malwared"}, "BitDefender": {"category": "harmless", "result": "clean", "method": "blacklist", "engine_name": "BitDefender"}, "GreenSnow": {"category": "harmless", "result": "clean", "method": "blacklist", "engine_name": "GreenSnow"}, "G-Data": {"category": "harmless", "result": "clean", "method": "blacklist", "engine_name": "G-Data"}, "VIPRE": {"category": "undetected", "result": "unrated", "method": "blacklist", "engine_name": "VIPRE"}, "SCUMWARE.org": {"category": "harmless", "result": "clean", "method": "blacklist", "engine_name": "SCUMWARE.org"}, "PhishFort": {"category": "undetected", "result": "unrated", "method": "blacklist", "engine_name": "PhishFort"}, "malwares.com URL checker": {"category": "harmless", "result": "clean", "method": "blacklist", "engine_name": "malwares.com URL checker"}, "Forcepoint ThreatSeeker": {"category": "harmless", "result": "clean", "method": "blacklist", "engine_name": "Forcepoint ThreatSeeker"}, "Criminal IP": {"category": "undetected", "result": "unrated", "method": "blacklist", "engine_name": "Criminal IP"}, "Certego": {"category": "harmless", "result": "clean", "method": "blacklist", "engine_name": "Certego"}, "ESET": {"category": "harmless", "result": "clean", "method": "blacklist", "engine_name": "ESET"}, "Threatsourcing": {"category": "harmless", "result": "clean", "method": "blacklist", "engine_name": "Threatsourcing"}, "ThreatHive": {"category": "harmless", "result": "clean", "method": "blacklist", "engine_name": "ThreatHive"}, "Bfore.Ai PreCrime": {"category": "harmless", "result": "clean", "method": "blacklist", "engine_name": "Bfore.Ai PreCrime"}}, "last_update_date": 1568043544, "last_modification_date": 1686521855, "tld": "com", "last_https_certificate": {"size": 1163, "public_key": {"ec": {"oid": "secp256r1", "pub": "3059301306072a8648ce3d020106082a8648ce3d03010703420004e7e24ed3b505f9892a53b187bef3c5045b932386de114793b54aeb5d70d5938ff204c03b69f15552888de131777f5891f5961bdfda1fc5079123789bbc37281f"}, "algorithm": "EC"}, "thumbprint_sha256": "de323320be6ab0baf76489cc96737ba3816b45e3b0fedd1fd52322421615e027", "cert_signature": {"signature": "d06e113930604073ac15eebb58723323a54e0d8f94e8e200adff26b27c5f138d581f6f2771e998a60f41aea11ad3b65e5410e010c35d6c26797acb3372daf4d7f890c1cceca9a14d4bba352c9c20dbaf178c36f0ac643f4cbe5513699af9bb93bdb7c4693eec5923761a403210fbdf6d8531996a615df00d10c41da4833599c19d39e235a5b1f9c5e33ef9461eb632a23699d91efe71030653ef937ef19eca43eda27f8adc23eb180d0d828871cf2a8ecb9c753f2dd1b4bad46421f2dc9bb1b6e5ff16f94c5c3bb4600a141dfaa1981a12a968fcb072dbfbe7397780163b8ae18c716f178fc254792ec5e84a976cadc06219aa2b0959184e898ab4aea8f380b4", "signature_algorithm": "sha256RSA"}, "validity": {"not_after": "2023-08-11 12:58:12", "not_before": "2023-05-19 12:58:13"}, "version": "V3", "extensions": {"certificate_policies": ["2.23.140.1.2.1", "1.3.6.1.4.1.11129.2.5.3"], "extended_key_usage": ["serverAuth"], "authority_key_identifier": {"keyid": "8a747faf85cdee95cd3d9cd0e24614f371351d27"}, "subject_alternative_name": ["www.google.com"], "subject_key_identifier": "95c5e6af1cd6d2002a8abfd76b26db39ec94fa07", "crl_distribution_points": ["http://crls.pki.goog/gts1c3/fVJxbV-Ktmk.crl"], "key_usage": ["digitalSignature"], "1.3.6.1.4.1.11129.2.4.2": "0481f200f0007600e83ed0da3ef5063532e75728bc896bc903d3cbd1116beceb", "CA": false, "ca_information_access": {"CA Issuers": "http://pki.goog/repo/certs/gts1c3.der", "OCSP": "http://ocsp.pki.goog/gts1c3"}}, "thumbprint": "a895c3cbd63fbc0a7dff36725e2f56269feb770e", "serial_number": "688a9d708922429412bb41ddc046521", "issuer": {"C": "US", "CN": "GTS CA 1C3", "O": "Google Trust Services LLC"}, "subject": {"CN": "www.google.com"}}, "categories": {"Forcepoint ThreatSeeker": "search engines and portals", "Sophos": "search engines", "BitDefender": "searchengines"}, "total_votes": {"harmless": 72, "malicious": 14}}, "type": "domain", "id": "www.google.com", "links": {"self": "https://www.virustotal.com/api/v3/domains/www.google.com"}}}}}, "test": {"entities": {"123": "4566"}}, "elastic_siem": {"entities": {"ODkzYjNkNDAtYTdiNy00MjdjLWJhYjItM2U4NGEzZjMzNWMxLTkwMjAtMTY4NDUxMjc4Mi44MTkzMTM2MDA=": {"agent": {"id": "893b3d40-a7b7-427c-bab2-3e84a3f335c1", "type": "endpoint", "version": "8.5.2"}, "process": {"Ext": {"ancestry": ["ODkzYjNkNDAtYTdiNy00MjdjLWJhYjItM2U4NGEzZjMzNWMxLTExNzQ4LTE2ODQ1MTI3ODIuNjQ0Mzk3ODAw", "ODkzYjNkNDAtYTdiNy00MjdjLWJhYjItM2U4NGEzZjMzNWMxLTEwMjkyLTE2ODQ1MTE3NDUuMzg4MjA4NjAw", "ODkzYjNkNDAtYTdiNy00MjdjLWJhYjItM2U4NGEzZjMzNWMxLTIwNjU2LTE2ODQ1MTE3NDUuMTQ3NjE3MjAw", "ODkzYjNkNDAtYTdiNy00MjdjLWJhYjItM2U4NGEzZjMzNWMxLTUzNi0xNjgxMTM5NzIyLjkxNDQ5OTQwMA==", "ODkzYjNkNDAtYTdiNy00MjdjLWJhYjItM2U4NGEzZjMzNWMxLTQtMTY4MTEzOTcyMi45MDQ1NDc5MDA=", "ODkzYjNkNDAtYTdiNy00MjdjLWJhYjItM2U4NGEzZjMzNWMxLTAtMTY4MTEzOTcyMi45MDQ1NDc5MDA="], "code_signature": [{"trusted": true, "subject_name": "Microsoft Windows", "exists": true, "status": "trusted"}]}, "parent": {"pid": 11748}, "code_signature": {"trusted": true, "subject_name": "Microsoft Windows", "exists": true, "status": "trusted"}, "name": "explorer.exe", "pid": 9020, "thread": {"id": 6112}, "entity_id": "ODkzYjNkNDAtYTdiNy00MjdjLWJhYjItM2U4NGEzZjMzNWMxLTkwMjAtMTY4NDUxMjc4Mi44MTkzMTM2MDA=", "executable": "C:\\Windows\\explorer.exe"}, "@timestamp": "2023-06-05T12:54:22.522291Z", "file": {"Ext": {"header_data": [], "entropy": 3.383684590882299, "header_bytes": "00acac006000000020000000688c0100", "windows": {"zone_identifier": -1}, "monotonic_id": 300310}, "path": "C:\\Users\\info\\AppData\\Local\\Microsoft\\Windows\\Caches\\{3DA71D5A-20CC-432F-A115-DFE92379E91F}.3.ver0x000000000000013f.db", "extension": "db", "size": 101480, "name": "{3DA71D5A-20CC-432F-A115-DFE92379E91F}.3.ver0x000000000000013f.db"}, "ecs": {"version": "1.11.0"}, "data_stream": {"namespace": "default", "type": "logs", "dataset": "endpoint.events.file"}, "elastic": {"agent": {"id": "893b3d40-a7b7-427c-bab2-3e84a3f335c1"}}, "host": {"hostname": "DARWINS-LAPTOP", "os": {"Ext": {"variant": "Windows 10 Home"}, "kernel": "22H2 (10.0.19045.2728)", "name": "Windows", "family": "windows", "type": "windows", "version": "22H2 (10.0.19045.2728)", "platform": "windows", "full": "Windows 10 Home 22H2 (10.0.19045.2728)"}, "ip": ["169.254.195.193", "fe80::b3fb:89bb:73b7:8f61", "10.21.1.2", "169.254.106.69", "fe80::cab3:5e75:a149:4b56", "169.254.99.149", "fe80::7ea2:27ab:28b5:47fd", "192.168.2.125", "2003:f7:a71b:2e6b:1baf:42f2:d0ab:4a0", "2003:f7:a71b:2e6b:3c9a:2de5:d03f:e9aa", "fe80::ae07:d611:231f:5e57", "169.254.58.69", "fe80::d0c6:cb8a:2892:3203", "127.0.0.1", "::1"], "name": "DARWINS-LAPTOP", "id": "afc827d3-e86d-432b-9b05-582675de39b4", "mac": ["e8:6a:64:a2:71:8c", "20:79:18:cf:e1:bd", "22:79:18:cf:e1:bc", "20:79:18:cf:e1:bc", "20:79:18:cf:e1:c0"], "architecture": "x86_64"}, "event": {"agent_id_status": "verified", "sequence": 1133277, "ingested": "2023-06-05T12:53:48Z", "created": "2023-06-05T12:54:22.522291Z", "kind": "event", "module": "endpoint", "action": "creation", "id": "N1Ec5JJq9pYb57KW++++HZbt", "category": ["file"], "type": ["creation"], "dataset": "endpoint.events.file"}, "message": "Endpoint file event", "user": {"domain": "DARWINS-LAPTOP", "name": "info", "id": "S-1-5-21-2653779196-1228881428-2247580809-1001"}}}, "successful_indices": ["logs-*"]}}